blambda/__init__.py
blambda/utils/__init__.py
blambda/utils/version.py
blambda-0.1.dist-info/DESCRIPTION.rst
blambda-0.1.dist-info/METADATA
blambda-0.1.dist-info/RECORD
blambda-0.1.dist-info/WHEEL
blambda-0.1.dist-info/metadata.json
blambda-0.1.dist-info/top_level.txt
